{"altLabel": [{"#text": "Кралство Бахрейн", "@lang": "bg"}, {"#text": "Království Bahrajn", "@lang": "cs"}, {"#text": "Kongeriget Bahrain", "@lang": "da"}, {"#text": "Königreich Bahrain", "@lang": "de"}, {"#text": "Βασίλειο του Μπαχρέιν", "@lang": "el"}, {"#text": "Kingdom of Bahrain", "@lang": "en"}, {"#text": "Bahreini Kuningriik", "@lang": "et"}, {"#text": "Bahrainin kuningaskunta", "@lang": "fi"}, {"#text": "Royaume de Bahreïn", "@lang": "fr"}, {"#text": "Ríocht Bhairéin", "@lang": "ga"}, {"#text": "Kraljevina Bahrein", "@lang": "hr"}, {"#text": "Bahreini Királyság", "@lang": "hu"}, {"#text": "Regno del Bahrein", "@lang": "it"}, {"#text": "Bahreinas Karaliste", "@lang": "lv"}, {"#text": "Bahreino Karalystė", "@lang": "lt"}, {"#text": "Ir-Renju tal-Baħrejn", "@lang": "mt"}, {"#text": "Koninkrijk Bahrein", "@lang": "nl"}, {"#text": "Królestwo Bahrajnu", "@lang": "pl"}, {"#text": "Reino do Barém", "@lang": "pt"}, {"#text": "Regatul Bahrain", "@lang": "ro"}, {"#text": "Bahrajnské kráľovstvo", "@lang": "sk"}, {"#text": "Kraljevina Bahrajn", "@lang": "sl"}, {"#text": "Reino de Bahréin", "@lang": "es"}, {"#text": "Konungariket Bahrain", "@lang": "sv"}], "authority-code": "BHR", "about": "http://publications.europa.eu/resource/authority/country/BHR", "identifier": "BHR", "prefLabel": [{"#text": "Бахрейн", "@lang": "bg"}, {"#text": "Bahrajn", "@lang": "cs"}, {"#text": "Bahrain", "@lang": "da"}, {"#text": "Bahrain", "@lang": "de"}, {"#text": "Μπαχρέιν", "@lang": "el"}, {"#text": "Bahrain", "@lang": "en"}, {"#text": "Bahrein", "@lang": "et"}, {"#text": "Bahrain", "@lang": "fi"}, {"#text": "Bahreïn", "@lang": "fr"}, {"#text": "Bairéin", "@lang": "ga"}, {"#text": "Bahrein", "@lang": "hr"}, {"#text": "Bahrein", "@lang": "hu"}, {"#text": "Bahrein", "@lang": "it"}, {"#text": "Bahreina", "@lang": "lv"}, {"#text": "Bahreinas", "@lang": "lt"}, {"#text": "Il-Baħrejn", "@lang": "mt"}, {"#text": "Bahrein", "@lang": "nl"}, {"#text": "Bahrajn", "@lang": "pl"}, {"#text": "Barém", "@lang": "pt"}, {"#text": "Bahrain", "@lang": "ro"}, {"#text": "Bahrajn", "@lang": "sk"}, {"#text": "Bahrajn", "@lang": "sl"}, {"#text": "Bahréin", "@lang": "es"}, {"#text": "Bahrain", "@lang": "sv"}], "start.use": "1976-12-16", "deprecated": "false"}