{"altLabel": {"#text": "N/A", "@lang": "N/A"}, "authority-code": "GLP", "about": "http://publications.europa.eu/resource/authority/country/GLP", "identifier": "GLP", "prefLabel": [{"#text": "Гваделупа", "@lang": "bg"}, {"#text": "Guadeloupe", "@lang": "cs"}, {"#text": "Guadeloupe", "@lang": "da"}, {"#text": "Guadeloupe", "@lang": "de"}, {"#text": "Γουαδελούπη", "@lang": "el"}, {"#text": "Guadeloupe", "@lang": "en"}, {"#text": "Guadeloupe", "@lang": "et"}, {"#text": "Guadeloupe", "@lang": "fi"}, {"#text": "Guadeloupe", "@lang": "fr"}, {"#text": "Guadalúip", "@lang": "ga"}, {"#text": "Guadeloupe", "@lang": "hr"}, {"#text": "Guadeloupe", "@lang": "hu"}, {"#text": "Guadalupa", "@lang": "it"}, {"#text": "Gvadelupa", "@lang": "lv"}, {"#text": "Gvadelupa", "@lang": "lt"}, {"#text": "Il-Gwadelup", "@lang": "mt"}, {"#text": "Guadeloupe", "@lang": "nl"}, {"#text": "Gwadelupa", "@lang": "pl"}, {"#text": "Guadalupe", "@lang": "pt"}, {"#text": "Guadelupa", "@lang": "ro"}, {"#text": "Guadeloupe", "@lang": "sk"}, {"#text": "Gvadelup", "@lang": "sl"}, {"#text": "Guadalupe", "@lang": "es"}, {"#text": "Guadeloupe", "@lang": "sv"}], "start.use": "1950-05-09", "deprecated": "false"}