{"altLabel": [{"#text": "Република Екваториална Гвинея", "@lang": "bg"}, {"#text": "Republika Rovníková Guinea", "@lang": "cs"}, {"#text": "Republikken Ækvatorialguinea", "@lang": "da"}, {"#text": "Republik Äquatorialguinea", "@lang": "de"}, {"#text": "Δημοκρατία της Ισημερινής Γουινέας", "@lang": "el"}, {"#text": "Republic of Equatorial Guinea", "@lang": "en"}, {"#text": "Ekvatoriaal-Guinea Vabariik", "@lang": "et"}, {"#text": "Päiväntasaajan Guinean tasavalta", "@lang": "fi"}, {"#text": "République de Guinée équatoriale", "@lang": "fr"}, {"#text": "Poblacht na Guine Meánchiorclaí", "@lang": "ga"}, {"#text": "Republika Ekvatorska Gvineja", "@lang": "hr"}, {"#text": "Egyenlítői-guineai Köztársaság", "@lang": "hu"}, {"#text": "Repubblica della Guinea equatoriale", "@lang": "it"}, {"#text": "Ekvatoriālās Gvinejas Republika", "@lang": "lv"}, {"#text": "Pusiaujo Gvinėjos Respublika", "@lang": "lt"}, {"#text": "Ir-Repubblika tal-Ginea Ekwatorjali", "@lang": "mt"}, {"#text": "Republiek Equatoriaal-Guinea", "@lang": "nl"}, {"#text": "Republika Gwinei Równikowej", "@lang": "pl"}, {"#text": "República da Guiné Equatorial", "@lang": "pt"}, {"#text": "Republica Guineea Ecuatorială", "@lang": "ro"}, {"#text": "Republika Rovníkovej Guiney", "@lang": "sk"}, {"#text": "Republika Ekvatorialna Gvineja", "@lang": "sl"}, {"#text": "República de Guinea Ecuatorial", "@lang": "es"}, {"#text": "Republiken Ekvatorialguinea", "@lang": "sv"}], "authority-code": "GNQ", "about": "http://publications.europa.eu/resource/authority/country/GNQ", "identifier": "GNQ", "prefLabel": [{"#text": "Екваториална Гвинея", "@lang": "bg"}, {"#text": "Rovníková Guinea", "@lang": "cs"}, {"#text": "Ækvatorialguinea", "@lang": "da"}, {"#text": "Äquatorialguinea", "@lang": "de"}, {"#text": "Ισημερινή Γουινέα", "@lang": "el"}, {"#text": "Equatorial Guinea", "@lang": "en"}, {"#text": "Ekvatoriaal-Guinea", "@lang": "et"}, {"#text": "Päiväntasaajan Guinea", "@lang": "fi"}, {"#text": "Guinée équatoriale", "@lang": "fr"}, {"#text": "An Ghuine Mheánchiorclach", "@lang": "ga"}, {"#text": "Ekvatorska Gvineja", "@lang": "hr"}, {"#text": "Egyenlítői-Guinea", "@lang": "hu"}, {"#text": "Guinea equatoriale", "@lang": "it"}, {"#text": "Ekvatoriālā Gvineja", "@lang": "lv"}, {"#text": "Pusiaujo Gvinėja", "@lang": "lt"}, {"#text": "Il-Ginea Ekwatorjali", "@lang": "mt"}, {"#text": "Equatoriaal-Guinea", "@lang": "nl"}, {"#text": "Gwinea Równikowa", "@lang": "pl"}, {"#text": "Guiné Equatorial", "@lang": "pt"}, {"#text": "Guineea Ecuatorială", "@lang": "ro"}, {"#text": "Rovníková Guinea", "@lang": "sk"}, {"#text": "Ekvatorialna Gvineja", "@lang": "sl"}, {"#text": "Guinea Ecuatorial", "@lang": "es"}, {"#text": "Ekvatorialguinea", "@lang": "sv"}], "start.use": "1968-10-12", "deprecated": "false"}