{"altLabel": [{"#text": "Расійская Федэрацыя", "@lang": "be"}, {"#text": "Ruska Federacija", "@lang": "bs"}, {"#text": "Руска федерация", "@lang": "bg"}, {"#text": "Federació Russa", "@lang": "ca"}, {"#text": "Ruská federace", "@lang": "cs"}, {"#text": "Den Russiske Føderation", "@lang": "da"}, {"#text": "Russische Föderation", "@lang": "de"}, {"#text": "Ρωσική Ομοσπονδία", "@lang": "el"}, {"#text": "Russian Federation", "@lang": "en"}, {"#text": "Venemaa Föderatsioon", "@lang": "et"}, {"#text": "Errusiar Federazioa", "@lang": "eu"}, {"#text": "Sambandsríki Russland", "@lang": "fo"}, {"#text": "Venäjän federaatio", "@lang": "fi"}, {"#text": "Fédération de Russie", "@lang": "fr"}, {"#text": "Cónaidhm na Rúise", "@lang": "ga"}, {"#text": "Federación Rusa", "@lang": "gl"}, {"#text": "Ruska Federacija", "@lang": "hr"}, {"#text": "Oroszországi Föderáció", "@lang": "hu"}, {"#text": "Rússneska sambandsríkið", "@lang": "is"}, {"#text": "Federazione Russa", "@lang": "it"}, {"#text": "Krievijas Federācija", "@lang": "lv"}, {"#text": "Rusijos Federacija", "@lang": "lt"}, {"#text": "Руската Федерација", "@lang": "mk"}, {"#text": "Il-Federazzjoni Russa", "@lang": "mt"}, {"#text": "Russische Federatie", "@lang": "nl"}, {"#text": "Den russiske føderasjonen", "@lang": "no"}, {"#text": "Federacja Rosyjska", "@lang": "pl"}, {"#text": "Federação da Rússia", "@lang": "pt"}, {"#text": "Federaziun russa", "@lang": "rm"}, {"#text": "Federaţia Rusă", "@lang": "ro"}, {"#text": "Российская Федерация", "@lang": "ru"}, {"#text": "Ruská federácia", "@lang": "sk"}, {"#text": "Ruska federacija", "@lang": "sl"}, {"#text": "Federación Rusa", "@lang": "es"}, {"#text": "Federata Ruse", "@lang": "sq"}, {"#text": "Руска Федерација", "@lang": "sr"}, {"#text": "Ryska federationen", "@lang": "sv"}, {"#text": "Rusya Federasyonu", "@lang": "tr"}, {"#text": "Російська Федерація", "@lang": "uk"}], "authority-code": "RUS", "about": "http://publications.europa.eu/resource/authority/country/RUS", "identifier": "RUS", "prefLabel": [{"#text": "Расія", "@lang": "be"}, {"#text": "Rusija", "@lang": "bs"}, {"#text": "Русия", "@lang": "bg"}, {"#text": "Rússia", "@lang": "ca"}, {"#text": "Rusko", "@lang": "cs"}, {"#text": "Rusland", "@lang": "da"}, {"#text": "Russland", "@lang": "de"}, {"#text": "Ρωσία", "@lang": "el"}, {"#text": "Russia", "@lang": "en"}, {"#text": "Venemaa", "@lang": "et"}, {"#text": "Errusia", "@lang": "eu"}, {"#text": "Russland", "@lang": "fo"}, {"#text": "Venäjä", "@lang": "fi"}, {"#text": "Russie", "@lang": "fr"}, {"#text": "An Rúis", "@lang": "ga"}, {"#text": "Rusia", "@lang": "gl"}, {"#text": "Rusija", "@lang": "hr"}, {"#text": "Oroszország", "@lang": "hu"}, {"#text": "Rússland", "@lang": "is"}, {"#text": "Russia", "@lang": "it"}, {"#text": "Krievija", "@lang": "lv"}, {"#text": "Rusija", "@lang": "lt"}, {"#text": "Русија", "@lang": "mk"}, {"#text": "Ir-Russja", "@lang": "mt"}, {"#text": "Rusland", "@lang": "nl"}, {"#text": "Russland", "@lang": "no"}, {"#text": "Rosja", "@lang": "pl"}, {"#text": "Rússia", "@lang": "pt"}, {"#text": "Russia", "@lang": "rm"}, {"#text": "Rusia", "@lang": "ro"}, {"#text": "Россия", "@lang": "ru"}, {"#text": "Rusko", "@lang": "sk"}, {"#text": "Rusija", "@lang": "sl"}, {"#text": "Rusia", "@lang": "es"}, {"#text": "Rusia", "@lang": "sq"}, {"#text": "Русија", "@lang": "sr"}, {"#text": "Ryssland", "@lang": "sv"}, {"#text": "Rusya", "@lang": "tr"}, {"#text": "Росія", "@lang": "uk"}], "start.use": "1991-12-26", "deprecated": "false"}